gdscript_to_docs/__init__.py
gdscript_to_docs/__main__.py
gdscript_to_docs/_version.py
gdscript_to_docs/bbcode.py
gdscript_to_docs/cli.py
gdscript_to_docs/indexer.py
gdscript_to_docs/models.py
gdscript_to_docs/parser.py
gdscript_to_docs/references.py
gdscript_to_docs/regexes.py
gdscript_to_docs/render.py
gdscript_to_docs/utils.py
gdscript_to_docs/writer.py
gdscript_to_docs-0.1.5.dist-info/licenses/LICENSE
gdscript_to_docs-0.1.5.dist-info/METADATA
gdscript_to_docs-0.1.5.dist-info/WHEEL
gdscript_to_docs-0.1.5.dist-info/entry_points.txt
gdscript_to_docs-0.1.5.dist-info/top_level.txt
gdscript_to_docs-0.1.5.dist-info/RECORD
