Metadata-Version: 2.4
Name: gdscript-to-docs
Version: 0.1.5
Summary: GDScript documentation extractor and Markdown renderer
Author: Phase Line Studios
License: MIT License
Requires-Python: >=3.12
License-File: LICENSE
Provides-Extra: dev
Requires-Dist: pytest>=8; extra == "dev"
Requires-Dist: ruff>=0.5; extra == "dev"
Requires-Dist: mypy>=1.8; extra == "dev"
Dynamic: license-file
